CONTRIBUTING.md
LICENSE
MANIFEST.in
README.rst
setup.cfg
setup.py
youtube_music_uploader/__init__.py
youtube_music_uploader/auth.py
youtube_music_uploader/deduplicate.py
youtube_music_uploader/uploader_daemon.py
youtube_music_uploader.egg-info/PKG-INFO
youtube_music_uploader.egg-info/SOURCES.txt
youtube_music_uploader.egg-info/dependency_links.txt
youtube_music_uploader.egg-info/entry_points.txt
youtube_music_uploader.egg-info/requires.txt
youtube_music_uploader.egg-info/top_level.txt