Metadata-Version: 2.1
Name: youtube-music-uploader
Version: 1.3.2
Summary: Youtube Music package to upload your music library to Youtube Music
Home-page: https://github.com/jaymoulin/youtube-music-uploader/
Author: Jay MOULIN
License: MIT
Platform: UNKNOWN
Classifier: Development Status :: 5 - Production/Stable
Classifier: Programming Language :: Python
Classifier: License :: OSI Approved :: MIT License
Classifier: Natural Language :: English
Classifier: Operating System :: OS Independent
Classifier: Programming Language :: Python :: 3
Classifier: Programming Language :: Python :: 3.4
Classifier: Programming Language :: Python :: 3.5
Classifier: Programming Language :: Python :: 3.6
Classifier: Programming Language :: Python :: 3.7
Classifier: Programming Language :: Python :: 3.8
Classifier: Programming Language :: Python :: 3.9
Classifier: Programming Language :: Python :: 3.10
Classifier: Programming Language :: Python :: 3.11
Classifier: Programming Language :: Python :: 3.12
Classifier: Topic :: Communications :: File Sharing
Classifier: Topic :: Artistic Software
Classifier: Topic :: Internet :: File Transfer Protocol (FTP)
Classifier: Topic :: Home Automation
Classifier: Topic :: Internet
Classifier: Topic :: Multimedia :: Sound/Audio
Requires-Python: >=3
License-File: LICENSE
